CHANGES.rst
DESCRIPTION.rst
LICENSE
MANIFEST.in
README.md
setup.py
src/adc_visualization/__init__.py
src/adc_visualization/class_lister.py
src/adc_visualization/writer/__init__.py
src/adc_visualization/writer/_mel_spectrogram.py
src/adc_visualization/writer/_mfcc_spectrogram.py
src/adc_visualization/writer/_output_types.py
src/adc_visualization/writer/_stft_spectrogram.py
src/audio_dataset_converter_visualization.egg-info/PKG-INFO
src/audio_dataset_converter_visualization.egg-info/SOURCES.txt
src/audio_dataset_converter_visualization.egg-info/dependency_links.txt
src/audio_dataset_converter_visualization.egg-info/entry_points.txt
src/audio_dataset_converter_visualization.egg-info/requires.txt
src/audio_dataset_converter_visualization.egg-info/top_level.txt