Metadata-Version: 2.1
Name: audio-dataset-converter-visualization
Version: 0.0.3
Summary: Python3 library that adds visualization supportto the audio-dataset-converter library.
Home-page: https://github.com/waikato-llm/audio-dataset-converter-visualization
Author: Peter Reutemann
Author-email: fracpete@waikato.ac.nz
License: MIT License
Classifier: Development Status :: 4 - Beta
Classifier: License :: OSI Approved :: MIT License
Classifier: Topic :: Scientific/Engineering :: Artificial Intelligence
Classifier: Programming Language :: Python :: 3
License-File: LICENSE
